<odoo>
    <record id="action_report_school_leave" model="ir.actions.report">
        <field name="name">Leave Report</field>
        <field name="model">school.leave</field>
        <field name="report_type">qweb-pdf</field>
        <field name="report_name">school_management.report_leave</field>
        <field name="report_file">school_management.report_leave</field>
        <field name="binding_model_id" ref="school_management.model_school_leave"/>
        <field name="binding_type">report</field>
    </record>
</odoo>